MANIFEST.in
README.rst
setup.py
nemo_oauth_plugin/__init__.py
nemo_oauth_plugin.egg-info/PKG-INFO
nemo_oauth_plugin.egg-info/SOURCES.txt
nemo_oauth_plugin.egg-info/dependency_links.txt
nemo_oauth_plugin.egg-info/not-zip-safe
nemo_oauth_plugin.egg-info/requires.txt
nemo_oauth_plugin.egg-info/top_level.txt
nemo_oauth_plugin/data/assets/css/nemo_oauth_plugin.css
nemo_oauth_plugin/data/templates/authorized.html
nemo_oauth_plugin/data/templates/user.html