Metadata-Version: 1.0
Name: nemo-oauth-plugin
Version: 0.0.4
Summary: OAuth2 Plugin for Nemo
Home-page: https://github.com/Capitains/nemo-oauth-plugin
Author: Bridget Almas
Author-email: balmas@gmail.com
License: GNU GPL
Platform: UNKNOWN
